PyLayoutTools/__init__.py
PyLayoutTools/pltBox.py
PyLayoutTools/pltTable.py
pylayouttools-1.0.0.dist-info/licenses/LICENSE
pylayouttools-1.0.0.dist-info/METADATA
pylayouttools-1.0.0.dist-info/WHEEL
pylayouttools-1.0.0.dist-info/top_level.txt
pylayouttools-1.0.0.dist-info/RECORD
