Metadata-Version: 2.4
Name: PyLayoutTools
Version: 1.0.0
Summary: Library for Python Layouts
Author-email: Bash Elliott <rackodo.business@gmail.com>
License-Expression: GPL-3.0-only
Project-URL: Homepage, https://github.com/rackodo/PyLayoutTools
Project-URL: Bug Tracker, https://github.com/rackodo/PyLayoutTools/issues
Classifier: Programming Language :: Python :: 3
Classifier: Operating System :: OS Independent
Requires-Python: >=3.7
License-File: LICENSE
Dynamic: license-file
